account_service_client/__init__.py
account_service_client/client.py
usf_account_service_client-0.0.7.dist-info/METADATA
usf_account_service_client-0.0.7.dist-info/WHEEL
usf_account_service_client-0.0.7.dist-info/top_level.txt
usf_account_service_client-0.0.7.dist-info/RECORD
