Metadata-Version: 2.1
Name: usf-account-service-client
Version: 0.0.7
Summary: Account service client
Home-page: https://github.com/ukuspeed/usf-account-service
Author: Ukuspeed
Author-email: info@ukuspeed.gmail.com
License: UNKNOWN
Platform: UNKNOWN
Requires-Python: >=3.6
Requires-Dist: requests
Requires-Dist: us-libraries (>=0.0.14)
